{
  "skill_key": "analytics_google_com__eecabd76",
  "task_type": null,
  "domain": "analytics_google_com",
  "curated": false,
  "original_task": "Go to 'https://analytics.google.com/analytics/web/?pli=1#/a124382116p399448899/reports/explorer?params=_u..nav%3Dmaui%26_u.comparisonOption%3Ddisabled%26_u.date00%3D20260202%26_u.date01%3D20260215%26_r.explorerCard..rowsPerPage%3D25&collectionId=11113654410&ruid=f4b7cbea-3789-4f4d-9df7-ba150bce3a52&r=all-pages-and-screens'. Set the date range from Feb 23, 2026 to Mar 1, 2026 in the date range selector (Use the following format E.g. Feb 2, 2026 - Feb 9, 2026). Then click Apply (use javascript to find and click the apply button as the coordinate clicks and enter key will not work). Once you click apply, the table will reload with new table data. This is important - Please wait for the table to reload after you have clicked apply, and only then go through table and return the page views for the top 15 urls for newly generated table. The page views are in the 'Views' column, that sits next to 'Active User' column. Please  return the views in the views column, and the url associated to the view count.",
  "last_updated": "2026-03-02T09:12:42.896041",
  "run_count": 1,
  "action_sequence": [
    "navigate",
    "wait",
    "click",
    "input",
    "input",
    "evaluate",
    "scroll",
    "done"
  ],
  "step_descriptions": [
    "Step 1:\nActions: [\n {\n  \"navigate\": {\n   \"url\": \"https://analytics.google.com/analytics/web/?pli=1#/a124382116p399448899/reports/explorer?params=_u..nav%3Dmaui%26_u.comparisonOption%3Ddisabled%26_u.date00%3D20260202%26_u.date01%3D20260215%26_r.explorerCard..rowsPerPage%3D25&collectionId=11113654410&ruid=f4b7cbea-3789-4f4d-9df7-ba150bce3a52&r=all-pages-and-screens\",\n   \"new_tab\": false\n  }\n }\n]\nResult 1: 🔗 Navigated to https://analytics.google.com/analytics/web/?pli=1#/a124382116p399448899/reports/explorer?params=_u..nav%3Dmaui%26_u.comparisonOption%3Ddisabled%26_u.date00%3D20260202%26_u.date01%3D20260215%26_r.explorerCard..rowsPerPage%3D25&collectionId=11113654410&ruid=f4b7cbea-3789-4f4d-9df7-ba150bce3a52&r=all-pages-and-screens\n",
    "Step 2:\nActions: [\n {\n  \"wait\": {\n   \"seconds\": 5\n  }\n }\n]\nResult 1: Waited for 5 seconds\n",
    "Step 3:\nActions: [\n {\n  \"click\": {\n   \"index\": 248\n  }\n }\n]\nResult 1: Clicked button role=combobox \"Custom \n Feb 2 - Feb 15, 2026\" aria-label=Open date range pick\n",
    "Step 4:\nActions: [\n {\n  \"input\": {\n   \"index\": 7560,\n   \"text\": \"02/23/2026\",\n   \"clear\": true\n  }\n },\n {\n  \"input\": {\n   \"index\": 7566,\n   \"text\": \"03/01/2026\",\n   \"clear\": true\n  }\n }\n]\nResult 1: Typed '02/23/2026'\nResult 2: Typed '03/01/2026'\n",
    "Step 5:\nActions: [\n {\n  \"evaluate\": {\n   \"code\": \"(function(){try{const buttons=document.querySelectorAll('button');for(let btn of buttons){if(btn.textContent.trim()==='Apply'){btn.click();return 'Clicked Apply button'}}const matButtons=document.querySelectorAll('mat-button,button[mat-button],button[mat-raised-button],button[mat-flat-button]');for(let btn of matButtons){if(btn.textContent.includes('Apply')){btn.click();return 'Clicked mat Apply button'}}return 'Apply button not found'}catch(e){return 'Error: '+e.message}})()\"\n  }\n }\n]\nResult 1: Clicked Apply button\n",
    "Step 6:\nActions: [\n {\n  \"scroll\": {\n   \"down\": true,\n   \"pages\": 1.0\n  }\n }\n]\nResult 1: 🔍 Scrolled down 719px\n",
    "Step 7:\nActions: [\n {\n  \"done\": {\n   \"text\": \"Here are the page views for the top 15 URLs from Google Analytics for the date range **Feb 23, 2026 - Mar 1, 2026**:\\n\\n| Rank | URL | Views |\\n|------|-----|-------|\\n| 1 | /guitar-tuner/ | 14,926 |\\n| 2 | /next-level-playing-sneak-peek/ | 14,890 |\\n| 3 | /learn-practice-play/ | 5,860 |\\n| 4 | /next-level-playing/ | 2,959 |\\n| 5 | /acoustic-adventure/ | 2,048 |\\n| 6 | / | 1,975 |\\n| 7 | /thank-you-quiz/ | 1,397 |\\n| 8 | /metronome/ | 1,060 |\\n| 9 | /courses/ | 980 |\\n| 10 | /electric-elevation/ | 934 |\\n| 11 | /guitar-chord-library/ | 810 |\\n| 12 | /free-3-part-mini-training/ | 605 |\\n| 13 | /loop-school/ | 570 |\\n| 14 | /next-level-playing-free-lesson/ | 269 |\\n| 15 | /personalized-practice-plan/ | 222 |\\n\\n**Total Views for period:** 50,965\",\n   \"success\": true,\n   \"files_to_display\": []\n  }\n }\n]\nResult 1: Here are the page views for the top 15 URLs from Google Analytics for the date range **Feb 23, 2026 - Mar 1, 2026**:\n\n| Rank | URL | Views |\n|------|-----|-------|\n| 1 | /guitar-tuner/ | 14,926 |\n| 2 | /next-level-playing-sneak-peek/ | 14,890 |\n| 3 | /learn-practice-play/ | 5,860 |\n| 4 | /next-level-playing/ | 2,959 |\n| 5 | /acoustic-adventure/ | 2,048 |\n| 6 | / | 1,975 |\n| 7 | /thank-you-quiz/ | 1,397 |\n| 8 | /metronome/ | 1,060 |\n| 9 | /courses/ | 980 |\n| 10 | /electric-elevation/ | 934 |\n| 11 | /guitar-chord-library/ | 810 |\n| 12 | /free-3-part-mini-training/ | 605 |\n| 13 | /loop-school/ | 570 |\n| 14 | /next-level-playing-free-lesson/ | 269 |\n| 15 | /personalized-practice-plan/ | 222 |\n\n**Total Views for period:** 50,965\n"
  ],
  "final_result_summary": "Here are the page views for the top 15 URLs from Google Analytics for the date range **Feb 23, 2026 - Mar 1, 2026**:\n\n| Rank | URL | Views |\n|------|-----|-------|\n| 1 | /guitar-tuner/ | 14,926 |\n| 2 | /next-level-playing-sneak-peek/ | 14,890 |\n| 3 | /learn-practice-play/ | 5,860 |\n| 4 | /next-level-playing/ | 2,959 |\n| 5 | /acoustic-adventure/ | 2,048 |\n| 6 | / | 1,975 |\n| 7 | /thank-you-quiz/ | 1,397 |\n| 8 | /metronome/ | 1,060 |\n| 9 | /courses/ | 980 |\n| 10 | /electric-elevation/ | 934 |\n| 11 | /guitar-chord-library/ | 810 |\n| 12 | /free-3-part-mini-training/ | 605 |\n| 13 | /loop-school/ | 570 |\n| 14 | /next-level-playing-free-lesson/ | 269 |\n| 15 | /personalized-practice-plan/ | 222 |\n\n**Total Views for period:** 50,965"
}